supervisor_shell_ui/__init__.py
supervisor_shell_ui/common.py
supervisor_shell_ui/config.py
supervisor_shell_ui/keys.py
supervisor_shell_ui/main.py
supervisor_shell_ui/page.py
supervisor_shell_ui/page_main.py
supervisor_shell_ui/page_tail.py
supervisor_shell_ui/screen.py
supervisor_shell_ui/supervisor.py
supervisor_shell_ui-0.3.0.dist-info/LICENSE
supervisor_shell_ui-0.3.0.dist-info/METADATA
supervisor_shell_ui-0.3.0.dist-info/WHEEL
supervisor_shell_ui-0.3.0.dist-info/entry_points.txt
supervisor_shell_ui-0.3.0.dist-info/top_level.txt
supervisor_shell_ui-0.3.0.dist-info/RECORD
