Metadata-Version: 2.1
Name: supervisor-shell-ui
Version: 0.3.0
Summary: A CLI alternative to the built-in web interface of Supervisor, offering a more convenient way to manage processes directly from the terminal.
Author: Ciprian Mandache
Author-email: psyb0t@51k.eu
License: GPL-3.0
Requires-Python: >=3.6
License-File: LICENSE
Requires-Dist: urllib3 ==1.26.16
Requires-Dist: requests ==2.31.0
Requires-Dist: requests-unixsocket ==0.3.0
